indiek/core/__init__.py
indiek/core/items.py
indiek/core/search.py
indiek_core-0.1.3.dist-info/LICENSE
indiek_core-0.1.3.dist-info/METADATA
indiek_core-0.1.3.dist-info/WHEEL
indiek_core-0.1.3.dist-info/top_level.txt
indiek_core-0.1.3.dist-info/RECORD
