Metadata-Version: 2.1
Name: indiek-core
Version: 0.1.3
Summary: core logic for indiek
Home-page: https://pypi.org/project/indiek-core/
Author: Adrian Ernesto Radillo
Author-email: adrian.radillo@gmail.com
License: GNU Affero General Public License v3.0
Project-URL: GitHub, https://github.com/indiek/indiek.core
Project-URL: Documentation, https://indiekcore.readthedocs.io/en/latest/
Requires-Python: >=3.8
License-File: LICENSE
Requires-Dist: indiek-mockdb (==0.1.3)
Provides-Extra: dev
Requires-Dist: pytest ; extra == 'dev'
Requires-Dist: pytest-pep8 ; extra == 'dev'
Requires-Dist: pytest-cov ; extra == 'dev'
